ppickle/__init__.py
ppickle-0.1.5.dist-info/METADATA
ppickle-0.1.5.dist-info/RECORD
ppickle-0.1.5.dist-info/WHEEL
ppickle-0.1.5.dist-info/top_level.txt
